python_markdown_maker/__init__.py
python_markdown_maker-1.0.dist-info/LICENSE
python_markdown_maker-1.0.dist-info/METADATA
python_markdown_maker-1.0.dist-info/WHEEL
python_markdown_maker-1.0.dist-info/top_level.txt
python_markdown_maker-1.0.dist-info/RECORD
