Metadata-Version: 2.1
Name: python-markdown-maker
Version: 1.0
Summary: Write Markdown in Pythonic way
Home-page: https://github.com/yogeshwaran01/python-markdown-maker
Author: Yogeshwaran R
Author-email: yogeshin247@gmail.com
License: MIT
Download-URL: https://github.com/yogeshwaran01/python-markdown-maker/archive/refs/heads/master.zip
Platform: UNKNOWN
Classifier: Programming Language :: Python :: 3
Classifier: License :: OSI Approved :: MIT License
Classifier: Operating System :: OS Independent
